plutous/__init__.py
plutous/trade/__init__.py
plutous/trade/crypto/__init__.py
plutous/trade/crypto/alembic.ini
plutous/trade/crypto/alerts/__init__.py
plutous/trade/crypto/alerts/base.py
plutous/trade/crypto/alerts/oi_variation.py
plutous/trade/crypto/alerts/price_diff.py
plutous/trade/crypto/alerts/price_variation.py
plutous/trade/crypto/alerts/volume_pct_variation.py
plutous/trade/crypto/alerts/volume_variation.py
plutous/trade/crypto/app/__init__.py
plutous/trade/crypto/app/main.py
plutous/trade/crypto/app/models.py
plutous/trade/crypto/bots/__init__.py
plutous/trade/crypto/bots/base.py
plutous/trade/crypto/bots/test.py
plutous/trade/crypto/bots/webhook.py
plutous/trade/crypto/cli/__init__.py
plutous/trade/crypto/cli/database.py
plutous/trade/crypto/cli/main.py
plutous/trade/crypto/collectors/__init__.py
plutous/trade/crypto/collectors/base.py
plutous/trade/crypto/collectors/funding_rate.py
plutous/trade/crypto/collectors/long_short_ratio.py
plutous/trade/crypto/collectors/ohlcv.py
plutous/trade/crypto/collectors/open_interest.py
plutous/trade/crypto/collectors/orderbook.py
plutous/trade/crypto/collectors/taker_buy_sell.py
plutous/trade/crypto/config.py
plutous/trade/crypto/enums/__init__.py
plutous/trade/crypto/enums/exchange.py
plutous/trade/crypto/enums/order_type.py
plutous/trade/crypto/exchanges/__init__.py
plutous/trade/crypto/exchanges/base/__init__.py
plutous/trade/crypto/exchanges/base/errors.py
plutous/trade/crypto/exchanges/binance.py
plutous/trade/crypto/exchanges/bitget.py
plutous/trade/crypto/exchanges/bitmex.py
plutous/trade/crypto/exchanges/bybit.py
plutous/trade/crypto/exchanges/coinbase.py
plutous/trade/crypto/exchanges/coinex.py
plutous/trade/crypto/exchanges/deribit.py
plutous/trade/crypto/exchanges/gateio.py
plutous/trade/crypto/exchanges/gemini.py
plutous/trade/crypto/exchanges/huobi.py
plutous/trade/crypto/exchanges/hyperliquid.py
plutous/trade/crypto/exchanges/kraken.py
plutous/trade/crypto/exchanges/kucoin.py
plutous_trade_crypto-0.0.96.dist-info/LICENSE
plutous_trade_crypto-0.0.96.dist-info/METADATA
plutous_trade_crypto-0.0.96.dist-info/WHEEL
plutous_trade_crypto-0.0.96.dist-info/RECORD
