Metadata-Version: 2.1
Name: plutous-trade-crypto
Version: 0.0.96
Summary: Plutous Crypto Trading Library
License: MIT
Author: Cheun Hong
Author-email: cheunhong@plutous.io
Requires-Python: >=3.11,<3.12
Classifier: Intended Audience :: Developers
Classifier: License :: OSI Approved :: MIT License
Classifier: Operating System :: OS Independent
Classifier: Programming Language :: Python :: 3
Classifier: Programming Language :: Python :: 3.11
Requires-Dist: aiohttp (==3.10.11)
Requires-Dist: ccxt (>=4.4.30)
Requires-Dist: pandas (>=1.5.2)
Requires-Dist: plutous-trade (>=0.0.1)
Requires-Dist: python-telegram-bot (==13.4)
